jbturtle/__init__.py
jbturtle/jbturtle.py
jbturtle/jupyterlab_jbturtle.py
jbturtle-0.2.6.dist-info/LICENSE
jbturtle-0.2.6.dist-info/METADATA
jbturtle-0.2.6.dist-info/WHEEL
jbturtle-0.2.6.dist-info/top_level.txt
jbturtle-0.2.6.dist-info/RECORD
