Metadata-Version: 2.1
Name: jbturtle
Version: 0.2.6
Summary: Simple turtle system for JupyterLab
Home-page: https://github.com/fiseki/jupyterlab-jbturtle
Author: Fumi.Iseki
Author-email: fumi.hax@gmail.com
License: BSD 3-Clause License
Download-URL: https://github.com/fiseki/jupyterlab-jbturtle
Platform: UNKNOWN
License-File: LICENSE
Requires-Dist: Pillow
